{
  "meta": {
    "client_code": "PCC",
    "generated_at": "2026-03-31T21:00:12.800152Z",
    "months_available": [
      "2025-10",
      "2025-11",
      "2025-12",
      "2026-01",
      "2026-02"
    ]
  },
  "months": {
    "2025-10": {
      "composite_score": 55.6,
      "ioptimize": [
        {
          "location": "Company Avg",
          "scheduler_compliance_avg": null,
          "scheduler_compliance_median": null,
          "avg_delay_avg": 14.85,
          "avg_delay_median": 16.0,
          "chair_utilization_avg": 98.36,
          "chair_utilization_median": 100.33,
          "tx_past_close_avg": 3.91,
          "tx_past_close_median": 3.0,
          "tx_mins_past_close_avg": 23.58,
          "tx_mins_past_close_median": 21.5,
          "mom_deltas": {},
          "vs_company": {},
          "outlier_flags": []
        },
        {
          "location": "Montery office",
          "scheduler_compliance_avg": null,
          "scheduler_compliance_median": null,
          "avg_delay_avg": 14.85,
          "avg_delay_median": 16.0,
          "chair_utilization_avg": 98.36,
          "chair_utilization_median": 100.33,
          "tx_past_close_avg": 3.91,
          "tx_past_close_median": 3.0,
          "tx_mins_past_close_avg": 23.58,
          "tx_mins_past_close_median": 21.5,
          "mom_deltas": {},
          "vs_company": {
            "avg_chair_utilization": "below",
            "avg_delay_mins": "below",
            "avg_treatment_mins_per_patient": "below",
            "avg_treatments_per_day": "below",
            "avg_chairs_per_nurse": "below",
            "avg_nurse_to_patient_chair_time": "below",
            "avg_patients_per_nurse": "below",
            "iassign_utilization": "below"
          },
          "outlier_flags": []
        }
      ],
      "iassign": [
        {
          "location": "Company Avg",
          "iassign_utilization_avg": 95.65,
          "patients_per_nurse_avg": 7.95,
          "patients_per_nurse_median": 7.79,
          "chairs_per_nurse_avg": 2.9,
          "chairs_per_nurse_median": 3.0,
          "nurse_utilization_avg": 82.95,
          "nurse_utilization_median": 83.6,
          "mom_deltas": {},
          "vs_company": {},
          "outlier_flags": []
        },
        {
          "location": "Montery office",
          "iassign_utilization_avg": 95.65,
          "patients_per_nurse_avg": 7.95,
          "patients_per_nurse_median": 7.79,
          "chairs_per_nurse_avg": 2.9,
          "chairs_per_nurse_median": 3.0,
          "nurse_utilization_avg": 82.95,
          "nurse_utilization_median": 83.6,
          "mom_deltas": {},
          "vs_company": {
            "avg_chair_utilization": "below",
            "avg_delay_mins": "below",
            "avg_treatment_mins_per_patient": "below",
            "avg_treatments_per_day": "below",
            "avg_chairs_per_nurse": "below",
            "avg_nurse_to_patient_chair_time": "below",
            "avg_patients_per_nurse": "below",
            "iassign_utilization": "below"
          },
          "outlier_flags": []
        }
      ],
      "benchmarks": {
        "company_avg": {
          "scheduler_compliance_avg": null,
          "avg_delay_avg": 14.85,
          "chair_utilization_avg": 98.36,
          "tx_past_close_avg": 3.91
        },
        "onco_benchmark": {}
      },
      "ai_insights": {
        "executive_summary": "",
        "highlights": [],
        "concerns": [],
        "recommendations": []
      }
    },
    "2025-11": {
      "composite_score": 59.0,
      "ioptimize": [
        {
          "location": "Company Avg",
          "scheduler_compliance_avg": null,
          "scheduler_compliance_median": null,
          "avg_delay_avg": 14.47,
          "avg_delay_median": 12.96,
          "chair_utilization_avg": 93.47,
          "chair_utilization_median": 93.39,
          "tx_past_close_avg": 2.88,
          "tx_past_close_median": 0.0,
          "tx_mins_past_close_avg": 23.34,
          "tx_mins_past_close_median": 0.0,
          "mom_deltas": {},
          "vs_company": {},
          "outlier_flags": []
        },
        {
          "location": "Monterey Office",
          "scheduler_compliance_avg": null,
          "scheduler_compliance_median": null,
          "avg_delay_avg": 14.47,
          "avg_delay_median": 12.96,
          "chair_utilization_avg": 93.47,
          "chair_utilization_median": 93.39,
          "tx_past_close_avg": 2.88,
          "tx_past_close_median": 0.0,
          "tx_mins_past_close_avg": 23.34,
          "tx_mins_past_close_median": 0.0,
          "mom_deltas": {},
          "vs_company": {
            "avg_chair_utilization": "below",
            "avg_delay_mins": "below",
            "avg_treatment_mins_per_patient": "below",
            "avg_treatments_per_day": "below"
          },
          "outlier_flags": []
        }
      ],
      "iassign": [
        {
          "location": "Copany Avg",
          "iassign_utilization_avg": 100.0,
          "patients_per_nurse_avg": 7.65,
          "patients_per_nurse_median": 7.47,
          "chairs_per_nurse_avg": 2.88,
          "chairs_per_nurse_median": 3.0,
          "nurse_utilization_avg": 77.08,
          "nurse_utilization_median": 77.47,
          "mom_deltas": {},
          "vs_company": {},
          "outlier_flags": []
        },
        {
          "location": "Montery Office",
          "iassign_utilization_avg": 100.0,
          "patients_per_nurse_avg": 7.65,
          "patients_per_nurse_median": 7.47,
          "chairs_per_nurse_avg": 2.88,
          "chairs_per_nurse_median": 3.0,
          "nurse_utilization_avg": 77.08,
          "nurse_utilization_median": 77.47,
          "mom_deltas": {},
          "vs_company": {},
          "outlier_flags": []
        }
      ],
      "benchmarks": {
        "company_avg": {
          "scheduler_compliance_avg": null,
          "avg_delay_avg": 14.47,
          "chair_utilization_avg": 93.47,
          "tx_past_close_avg": 2.88
        },
        "onco_benchmark": {}
      },
      "ai_insights": {
        "executive_summary": "",
        "highlights": [],
        "concerns": [],
        "recommendations": []
      }
    },
    "2025-12": {
      "composite_score": 64.2,
      "ioptimize": [
        {
          "location": "Company Avg",
          "scheduler_compliance_avg": null,
          "scheduler_compliance_median": null,
          "avg_delay_avg": 13.68,
          "avg_delay_median": 12.47,
          "chair_utilization_avg": 91.38,
          "chair_utilization_median": 94.35,
          "tx_past_close_avg": 2.38,
          "tx_past_close_median": 2.0,
          "tx_mins_past_close_avg": 26.74,
          "tx_mins_past_close_median": 17.6,
          "mom_deltas": {},
          "vs_company": {},
          "outlier_flags": []
        },
        {
          "location": "Montery Office",
          "scheduler_compliance_avg": null,
          "scheduler_compliance_median": null,
          "avg_delay_avg": 13.68,
          "avg_delay_median": 12.47,
          "chair_utilization_avg": 91.38,
          "chair_utilization_median": 94.35,
          "tx_past_close_avg": 2.38,
          "tx_past_close_median": 2.0,
          "tx_mins_past_close_avg": 26.74,
          "tx_mins_past_close_median": 17.6,
          "mom_deltas": {
            "avg_chairs_per_nurse": 0.31,
            "avg_nurse_to_patient_chair_time": 8.45,
            "avg_patients_per_nurse": 0.64,
            "iassign_utilization": 0.0
          },
          "vs_company": {
            "avg_chair_utilization": "below",
            "avg_delay_mins": "below",
            "avg_treatment_mins_per_patient": "below",
            "avg_treatments_per_day": "below",
            "avg_chairs_per_nurse": "below",
            "avg_nurse_to_patient_chair_time": "below",
            "avg_patients_per_nurse": "below",
            "iassign_utilization": "below"
          },
          "outlier_flags": []
        }
      ],
      "iassign": [
        {
          "location": "Company Avg",
          "iassign_utilization_avg": 100.0,
          "patients_per_nurse_avg": 8.29,
          "patients_per_nurse_median": 8.14,
          "chairs_per_nurse_avg": 3.19,
          "chairs_per_nurse_median": 3.0,
          "nurse_utilization_avg": 85.53,
          "nurse_utilization_median": 85.46,
          "mom_deltas": {},
          "vs_company": {},
          "outlier_flags": []
        },
        {
          "location": "Montery Office",
          "iassign_utilization_avg": 100.0,
          "patients_per_nurse_avg": 8.29,
          "patients_per_nurse_median": 8.14,
          "chairs_per_nurse_avg": 3.19,
          "chairs_per_nurse_median": 3.0,
          "nurse_utilization_avg": 85.53,
          "nurse_utilization_median": 85.46,
          "mom_deltas": {
            "avg_chairs_per_nurse": 0.31,
            "avg_nurse_to_patient_chair_time": 8.45,
            "avg_patients_per_nurse": 0.64,
            "iassign_utilization": 0.0
          },
          "vs_company": {
            "avg_chair_utilization": "below",
            "avg_delay_mins": "below",
            "avg_treatment_mins_per_patient": "below",
            "avg_treatments_per_day": "below",
            "avg_chairs_per_nurse": "below",
            "avg_nurse_to_patient_chair_time": "below",
            "avg_patients_per_nurse": "below",
            "iassign_utilization": "below"
          },
          "outlier_flags": []
        }
      ],
      "benchmarks": {
        "company_avg": {
          "scheduler_compliance_avg": null,
          "avg_delay_avg": 13.68,
          "chair_utilization_avg": 91.38,
          "tx_past_close_avg": 2.38
        },
        "onco_benchmark": {
          "scheduler_compliance_avg": null,
          "avg_delay_avg": 14.03,
          "chair_utilization_avg": 73.48,
          "tx_past_close_avg": 1.72
        }
      },
      "ai_insights": {
        "executive_summary": "",
        "highlights": [],
        "concerns": [],
        "recommendations": []
      }
    },
    "2026-01": {
      "composite_score": 54.8,
      "ioptimize": [
        {
          "location": "Company Avg",
          "scheduler_compliance_avg": 50.0,
          "scheduler_compliance_median": null,
          "avg_delay_avg": 13.65,
          "avg_delay_median": 13.47,
          "chair_utilization_avg": 93.73,
          "chair_utilization_median": 85.58,
          "tx_past_close_avg": 1.61,
          "tx_past_close_median": 0.0,
          "tx_mins_past_close_avg": 30.35,
          "tx_mins_past_close_median": 0.0,
          "mom_deltas": {},
          "vs_company": {},
          "outlier_flags": []
        },
        {
          "location": "Monterey office",
          "scheduler_compliance_avg": 50.0,
          "scheduler_compliance_median": null,
          "avg_delay_avg": 13.65,
          "avg_delay_median": 13.47,
          "chair_utilization_avg": 93.73,
          "chair_utilization_median": 85.58,
          "tx_past_close_avg": 1.61,
          "tx_past_close_median": 0.0,
          "tx_mins_past_close_avg": 30.35,
          "tx_mins_past_close_median": 0.0,
          "mom_deltas": {},
          "vs_company": {
            "avg_chair_utilization": "below",
            "avg_delay_mins": "below",
            "avg_treatment_mins_per_patient": "below",
            "avg_treatments_per_day": "below",
            "scheduler_compliance": "below",
            "avg_chairs_per_nurse": "below",
            "avg_nurse_to_patient_chair_time": "below",
            "avg_patients_per_nurse": "below",
            "iassign_utilization": "below"
          },
          "outlier_flags": []
        }
      ],
      "iassign": [
        {
          "location": "Company Avg",
          "iassign_utilization_avg": 100.0,
          "patients_per_nurse_avg": 8.59,
          "patients_per_nurse_median": 8.67,
          "chairs_per_nurse_avg": 3.09,
          "chairs_per_nurse_median": 3.0,
          "nurse_utilization_avg": 81.74,
          "nurse_utilization_median": 81.3,
          "mom_deltas": {},
          "vs_company": {},
          "outlier_flags": []
        },
        {
          "location": "Monterey office",
          "iassign_utilization_avg": 100.0,
          "patients_per_nurse_avg": 8.59,
          "patients_per_nurse_median": 8.67,
          "chairs_per_nurse_avg": 3.09,
          "chairs_per_nurse_median": 3.0,
          "nurse_utilization_avg": 81.74,
          "nurse_utilization_median": 81.3,
          "mom_deltas": {},
          "vs_company": {
            "avg_chair_utilization": "below",
            "avg_delay_mins": "below",
            "avg_treatment_mins_per_patient": "below",
            "avg_treatments_per_day": "below",
            "scheduler_compliance": "below",
            "avg_chairs_per_nurse": "below",
            "avg_nurse_to_patient_chair_time": "below",
            "avg_patients_per_nurse": "below",
            "iassign_utilization": "below"
          },
          "outlier_flags": []
        }
      ],
      "benchmarks": {
        "company_avg": {
          "scheduler_compliance_avg": 50.0,
          "avg_delay_avg": 13.65,
          "chair_utilization_avg": 93.73,
          "tx_past_close_avg": 1.61
        },
        "onco_benchmark": {
          "scheduler_compliance_avg": 58.16,
          "avg_delay_avg": 14.29,
          "chair_utilization_avg": 69.01,
          "tx_past_close_avg": 1.08
        }
      },
      "ai_insights": {
        "executive_summary": "",
        "highlights": [],
        "concerns": [],
        "recommendations": []
      }
    },
    "2026-02": {
      "composite_score": 55.8,
      "ioptimize": [
        {
          "location": "Company Avg",
          "scheduler_compliance_avg": 81.14,
          "scheduler_compliance_median": null,
          "avg_delay_avg": 13.5,
          "avg_delay_median": 12.76,
          "chair_utilization_avg": 86.96,
          "chair_utilization_median": 84.01,
          "tx_past_close_avg": 2.5,
          "tx_past_close_median": 2.5,
          "tx_mins_past_close_avg": 21.42,
          "tx_mins_past_close_median": 13.75,
          "mom_deltas": {},
          "vs_company": {},
          "outlier_flags": []
        },
        {
          "location": "Global Avg",
          "scheduler_compliance_avg": 76.73,
          "scheduler_compliance_median": null,
          "avg_delay_avg": 11.68,
          "avg_delay_median": null,
          "chair_utilization_avg": 67.95,
          "chair_utilization_median": null,
          "tx_past_close_avg": 1.06,
          "tx_past_close_median": null,
          "tx_mins_past_close_avg": 19.03,
          "tx_mins_past_close_median": null,
          "mom_deltas": {},
          "vs_company": {
            "avg_chair_utilization": "below",
            "avg_delay_mins": "below",
            "avg_treatment_mins_per_patient": "below",
            "avg_treatments_per_day": "below",
            "scheduler_compliance": "below",
            "avg_chairs_per_nurse": "above",
            "avg_nurse_to_patient_chair_time": "below",
            "avg_patients_per_nurse": "below",
            "iassign_utilization": "below"
          },
          "outlier_flags": []
        },
        {
          "location": "Montery Office",
          "scheduler_compliance_avg": 81.14,
          "scheduler_compliance_median": null,
          "avg_delay_avg": 13.5,
          "avg_delay_median": 12.76,
          "chair_utilization_avg": 86.96,
          "chair_utilization_median": 84.01,
          "tx_past_close_avg": 2.5,
          "tx_past_close_median": 2.5,
          "tx_mins_past_close_avg": 21.42,
          "tx_mins_past_close_median": 13.75,
          "mom_deltas": {},
          "vs_company": {
            "avg_chair_utilization": "below",
            "avg_delay_mins": "below",
            "avg_treatment_mins_per_patient": "below",
            "avg_treatments_per_day": "below",
            "scheduler_compliance": "below",
            "avg_chairs_per_nurse": "below",
            "avg_nurse_to_patient_chair_time": "below",
            "avg_patients_per_nurse": "below",
            "iassign_utilization": "below"
          },
          "outlier_flags": []
        }
      ],
      "iassign": [
        {
          "location": "Company Avg",
          "iassign_utilization_avg": 100.0,
          "patients_per_nurse_avg": 8.46,
          "patients_per_nurse_median": 8.46,
          "chairs_per_nurse_avg": 3.16,
          "chairs_per_nurse_median": 3.06,
          "nurse_utilization_avg": 80.35,
          "nurse_utilization_median": 80.22,
          "mom_deltas": {},
          "vs_company": {},
          "outlier_flags": []
        },
        {
          "location": "Global Avg",
          "iassign_utilization_avg": 95.06,
          "patients_per_nurse_avg": 5.84,
          "patients_per_nurse_median": null,
          "chairs_per_nurse_avg": 3.59,
          "chairs_per_nurse_median": null,
          "nurse_utilization_avg": 53.91,
          "nurse_utilization_median": null,
          "mom_deltas": {},
          "vs_company": {
            "avg_chair_utilization": "below",
            "avg_delay_mins": "below",
            "avg_treatment_mins_per_patient": "below",
            "avg_treatments_per_day": "below",
            "scheduler_compliance": "below",
            "avg_chairs_per_nurse": "above",
            "avg_nurse_to_patient_chair_time": "below",
            "avg_patients_per_nurse": "below",
            "iassign_utilization": "below"
          },
          "outlier_flags": []
        },
        {
          "location": "Montery Office",
          "iassign_utilization_avg": 100.0,
          "patients_per_nurse_avg": 8.46,
          "patients_per_nurse_median": 8.46,
          "chairs_per_nurse_avg": 3.16,
          "chairs_per_nurse_median": 3.06,
          "nurse_utilization_avg": 80.35,
          "nurse_utilization_median": 80.22,
          "mom_deltas": {},
          "vs_company": {
            "avg_chair_utilization": "below",
            "avg_delay_mins": "below",
            "avg_treatment_mins_per_patient": "below",
            "avg_treatments_per_day": "below",
            "scheduler_compliance": "below",
            "avg_chairs_per_nurse": "below",
            "avg_nurse_to_patient_chair_time": "below",
            "avg_patients_per_nurse": "below",
            "iassign_utilization": "below"
          },
          "outlier_flags": []
        }
      ],
      "benchmarks": {
        "company_avg": {
          "scheduler_compliance_avg": 81.14,
          "avg_delay_avg": 13.5,
          "chair_utilization_avg": 86.96,
          "tx_past_close_avg": 2.5
        },
        "onco_benchmark": {}
      },
      "ai_insights": {
        "executive_summary": "Monterey Office delivered a Performance Score of 56 out of 100 (where 50 represents the network average), positioning the clinic slightly above the midline. The clinic matched the company average on Scheduler Compliance (81.1% vs. 81.14%) and Avg Delay (13.5 mins vs. 13.5 mins), while Chair Utilization of 87.0% aligned closely with the company benchmark of 86.96%. The primary operational friction point is Treatments Past Closing, which averaged 2.5 daily in February\u2014an area worth addressing to protect team wellbeing and operational predictability.",
        "highlights": [
          "Monterey achieved 100.0% iAssign Utilization in February, reflecting complete adherence to the assignment system and demonstrating the clinic's discipline in adopting our scheduling tools. Nurse Utilization of 80.3% sits at a healthy operating level, neither stretched nor underutilized, allowing the care team to maintain quality while managing patient flow efficiently."
        ],
        "concerns": [
          "We noticed that 2.5 treatments running past closing time daily at Monterey represents a meaningful gap\u2014this metric carries operational and cultural weight that warrants attention. While Scheduler Compliance and Avg Delay both track at company benchmarks, the frequency of late-running treatments suggests that either schedule buffers may need calibration, patient arrivals may be clustering toward day-end, or unexpected procedure durations are elongating the day. A brief data review focused on which appointment slots most often overrun and whether iOptimize recommendations are being applied uniformly across all time slots could surface quick wins."
        ],
        "recommendations": [
          "We'd recommend scheduling a brief operational sync with the Monterey team to examine the root drivers of the 2.5 daily treatments past closing. A simple analysis of whether late overruns cluster in specific chairs, appointment types, or time-of-day windows could reveal whether the fix is scheduling-side (tighter buffers, revised slot mix) or execution-side (patient prep delays, procedure variance). This is not a compliance problem\u2014it's an optimization opportunity that the team is well-positioned to solve together."
        ]
      }
    }
  },
  "chatbot_context": {
    "kpi_definitions": {
      "scheduler_compliance": {
        "label": "Scheduler Compliance",
        "unit": "%",
        "higher_is_better": true,
        "explanation": "Percentage of appointments scheduled following iOptimize recommendations. Higher is better. Company average is typically 60-70%. OncoSmart benchmark target is 75%."
      },
      "avg_delay_mins": {
        "label": "Avg Delay",
        "unit": "mins",
        "higher_is_better": false,
        "explanation": "Average daily schedule delay in minutes. Lower is better. Measures how far behind the clinic is running on average."
      },
      "avg_treatments_per_day": {
        "label": "Tx Past Close/Day",
        "unit": "count",
        "higher_is_better": false,
        "explanation": "Average treatments running past treatment close per day (overtime patients per day). Lower is better."
      },
      "avg_treatment_mins_per_patient": {
        "label": "Tx Mins Past Close/Patient",
        "unit": "mins",
        "higher_is_better": false,
        "explanation": "Average treatment minutes past closing time per patient. Lower is better."
      },
      "avg_chair_utilization": {
        "label": "Chair Utilization",
        "unit": "%",
        "higher_is_better": true,
        "explanation": "Average chair utilization rate. Higher is better."
      },
      "iassign_utilization": {
        "label": "iAssign Utilization",
        "unit": "%",
        "higher_is_better": true,
        "explanation": "Percentage of nurse assignments completed via iAssign. Higher means more consistent, optimized assignments."
      },
      "avg_patients_per_nurse": {
        "label": "Patients/Nurse/Day",
        "unit": "count",
        "higher_is_better": null,
        "explanation": "Average patients per nurse per day. Context-dependent -- too high means understaffing, too low means inefficiency."
      },
      "avg_chairs_per_nurse": {
        "label": "Chairs/Nurse",
        "unit": "count",
        "higher_is_better": null,
        "explanation": "Average chairs assigned per nurse. Context-dependent."
      },
      "avg_nurse_to_patient_chair_time": {
        "label": "Nurse Utilization",
        "unit": "%",
        "higher_is_better": true,
        "explanation": "Average nurse-to-patient in-chair time per day. Higher is better."
      }
    },
    "data_notes": "Company Avg rows represent the network average across all locations for this client in the given month. Onco rows are global oncology benchmarks from the OncoSmart network. Rows named Global Avg, Network Avg, Total, or Overall are network-wide aggregates, not individual clinic locations. MoM (Month-over-Month) deltas compare the current month to the prior month. Composite scores are weighted 0 to 100 where 100 is best-in-class performance.",
    "historical_kpis": [
      {
        "month": "2025-10",
        "location": "Montery office",
        "scheduler_compliance_avg": null,
        "avg_delay_avg": 14.85,
        "chair_utilization_avg": 98.36,
        "tx_past_close_avg": 3.91
      },
      {
        "month": "2025-11",
        "location": "Monterey Office",
        "scheduler_compliance_avg": null,
        "avg_delay_avg": 14.47,
        "chair_utilization_avg": 93.47,
        "tx_past_close_avg": 2.88
      },
      {
        "month": "2025-12",
        "location": "Montery Office",
        "scheduler_compliance_avg": null,
        "avg_delay_avg": 13.68,
        "chair_utilization_avg": 91.38,
        "tx_past_close_avg": 2.38
      },
      {
        "month": "2026-01",
        "location": "Monterey office",
        "scheduler_compliance_avg": 50.0,
        "avg_delay_avg": 13.65,
        "chair_utilization_avg": 93.73,
        "tx_past_close_avg": 1.61
      },
      {
        "month": "2026-02",
        "location": "Global Avg",
        "scheduler_compliance_avg": 76.73,
        "avg_delay_avg": 11.68,
        "chair_utilization_avg": 67.95,
        "tx_past_close_avg": 1.06
      },
      {
        "month": "2026-02",
        "location": "Montery Office",
        "scheduler_compliance_avg": 81.14,
        "avg_delay_avg": 13.5,
        "chair_utilization_avg": 86.96,
        "tx_past_close_avg": 2.5
      }
    ]
  }
}